[
  {
    "data": "2026-07-18",
    "product_id": "MLB73668889",
    "nome": "Kit 3 Prendedor De Chupeta Bebê Menino Marinheiro Angu Bebê",
    "preco": 69.9,
    "preco_original": 99.9,
    "n_ofertas": 2,
    "item_id": "MLB4780144711",
    "seller_id": 193812182,
    "frete_gratis": true,
    "full": false,
    "permalink": "https://www.mercadolivre.com.br/p/MLB73668889",
    "imagem": "https://http2.mlstatic.com/D_NQ_NP_761244-MLA113256604357_062026-F.jpg",
    "tipo": "camada2",
    "enfileirado_em": "2026-07-18T21:13:13.232781+00:00"
  },
  {
    "data": "2026-07-18",
    "product_id": "MLB21454662",
    "nome": "Bioré Lenço Umedecido Demaquilante 10 Unidades",
    "preco": 35.9,
    "preco_original": 36.99,
    "n_ofertas": 1,
    "item_id": "MLB4053883783",
    "seller_id": 480265022,
    "frete_gratis": true,
    "full": true,
    "permalink": "https://www.mercadolivre.com.br/p/MLB21454662",
    "imagem": "https://http2.mlstatic.com/D_NQ_NP_723296-MLU74210781739_012024-F.jpg",
    "tipo": "camada2",
    "enfileirado_em": "2026-07-18T21:13:13.232781+00:00"
  },
  {
    "data": "2026-07-18",
    "product_id": "MLB42742843",
    "nome": "Kit 7 Peças Porta Chupeta Saboneteira Kit Higiene Bebê",
    "preco": 60.72,
    "preco_original": 67.47,
    "n_ofertas": 1,
    "item_id": "MLB5308415410",
    "seller_id": 19530594,
    "frete_gratis": true,
    "full": false,
    "permalink": "https://www.mercadolivre.com.br/p/MLB42742843",
    "imagem": "https://http2.mlstatic.com/D_NQ_NP_817291-MLA99545132698_122025-F.jpg",
    "tipo": "camada2",
    "enfileirado_em": "2026-07-18T21:13:13.232781+00:00"
  },
  {
    "data": "2026-07-18",
    "product_id": "MLB66918343",
    "nome": "Kit Limpeza Mamadeira Bebê Portátil Escovas Suporte Secador Rosa",
    "preco": 55.9,
    "preco_original": null,
    "n_ofertas": 1,
    "item_id": "MLB6612359606",
    "seller_id": 270876841,
    "frete_gratis": true,
    "full": false,
    "permalink": "https://www.mercadolivre.com.br/p/MLB66918343",
    "imagem": "https://http2.mlstatic.com/D_NQ_NP_877124-MLA109115845481_032026-F.jpg",
    "tipo": "camada2",
    "enfileirado_em": "2026-07-18T21:13:13.232781+00:00"
  },
  {
    "data": "2026-07-18",
    "product_id": "MLB53969172",
    "nome": "Kit Carrinho Bebê + Bebê Conforto Dourado",
    "preco": 2024.91,
    "preco_original": 2249.9,
    "n_ofertas": 1,
    "item_id": "MLB5593522546",
    "seller_id": 576840178,
    "frete_gratis": true,
    "full": false,
    "permalink": "https://www.mercadolivre.com.br/p/MLB53969172",
    "imagem": "https://http2.mlstatic.com/D_NQ_NP_773103-MLA95398166810_102025-F.jpg",
    "tipo": "camada2",
    "enfileirado_em": "2026-07-18T21:13:13.232781+00:00"
  },
  {
    "data": "2026-07-18",
    "product_id": "MLB74956969",
    "nome": "Cadeirinha para Carro Bebe Conforto Burigotto Cadeira Materna Gris Bebê Conforto para Bebê Passeio Cadeirinha para Carro Bebê Conforto",
    "preco": 560.0,
    "preco_original": null,
    "n_ofertas": 1,
    "item_id": "MLB7095880678",
    "seller_id": 207589950,
    "frete_gratis": true,
    "full": false,
    "permalink": "https://www.mercadolivre.com.br/p/MLB74956969",
    "imagem": "https://http2.mlstatic.com/D_NQ_NP_631490-MLA112912749388_072026-F.jpg",
    "tipo": "camada2",
    "enfileirado_em": "2026-07-18T21:13:13.232781+00:00"
  },
  {
    "data": "2026-07-18",
    "product_id": "MLB22802404",
    "nome": "Móbile Berço Bebê Espaçonave Baby - Dmb5804 Dm Toys",
    "preco": 113.49,
    "preco_original": 169.0,
    "n_ofertas": 1,
    "item_id": "MLB6713060516",
    "seller_id": 15967456,
    "frete_gratis": true,
    "full": false,
    "permalink": "https://www.mercadolivre.com.br/p/MLB22802404",
    "imagem": "https://http2.mlstatic.com/D_NQ_NP_647953-MLA109038578979_032026-F.jpg",
    "tipo": "camada2",
    "enfileirado_em": "2026-07-18T21:13:13.232781+00:00"
  },
  {
    "data": "2026-07-18",
    "product_id": "MLB52505054",
    "nome": "Capa Colchão Berço Matelado Impermeável",
    "preco": 35.9,
    "preco_original": null,
    "n_ofertas": 1,
    "item_id": "MLB5503032982",
    "seller_id": 20796520,
    "frete_gratis": true,
    "full": false,
    "permalink": "https://www.mercadolivre.com.br/p/MLB52505054",
    "imagem": "https://http2.mlstatic.com/D_NQ_NP_969389-MLA92588707685_092025-F.jpg",
    "tipo": "camada2",
    "enfileirado_em": "2026-07-18T21:13:13.232781+00:00"
  },
  {
    "data": "2026-07-18",
    "product_id": "MLB56137815",
    "nome": "Colchão Berço Americano D18 Baby Polar",
    "preco": 227.85,
    "preco_original": null,
    "n_ofertas": 1,
    "item_id": "MLB6487489808",
    "seller_id": 312480620,
    "frete_gratis": true,
    "full": false,
    "permalink": "https://www.mercadolivre.com.br/p/MLB56137815",
    "imagem": "https://http2.mlstatic.com/D_NQ_NP_976539-MLA99989846219_112025-F.jpg",
    "tipo": "camada2",
    "enfileirado_em": "2026-07-18T21:13:13.232781+00:00"
  },
  {
    "data": "2026-07-18",
    "product_id": "MLB63184199",
    "nome": "Trocador Fraldas Bebê Fixação Parede Dobrável Cor Cinza",
    "preco": 1059.0,
    "preco_original": 1199.0,
    "n_ofertas": 1,
    "item_id": "MLB4368133727",
    "seller_id": 3034343879,
    "frete_gratis": true,
    "full": true,
    "permalink": "https://www.mercadolivre.com.br/p/MLB63184199",
    "imagem": "https://http2.mlstatic.com/D_NQ_NP_951335-MLA101427915847_122025-F.jpg",
    "tipo": "camada2",
    "enfileirado_em": "2026-07-18T21:13:13.232781+00:00"
  },
  {
    "data": "2026-07-18",
    "product_id": "MLB61178331",
    "nome": "Tapete Atividades Infantil Bebê Dobrável Tatame Dupla Face",
    "preco": 78.89,
    "preco_original": null,
    "n_ofertas": 1,
    "item_id": "MLB4274327665",
    "seller_id": 70325633,
    "frete_gratis": true,
    "full": true,
    "permalink": "https://www.mercadolivre.com.br/p/MLB61178331",
    "imagem": "https://http2.mlstatic.com/D_NQ_NP_754764-MLA99444948678_112025-F.jpg",
    "tipo": "camada2",
    "enfileirado_em": "2026-07-18T21:13:13.232781+00:00"
  },
  {
    "data": "2026-07-18",
    "product_id": "MLB62412430",
    "nome": "Brastoy Brinquedo Educativo Blocos Magnético 130 Peças Brinquedo Educativo",
    "preco": 205.0,
    "preco_original": 232.0,
    "n_ofertas": 1,
    "item_id": "MLB6204743302",
    "seller_id": 2653731189,
    "frete_gratis": true,
    "full": false,
    "permalink": "https://www.mercadolivre.com.br/p/MLB62412430",
    "imagem": "https://http2.mlstatic.com/D_NQ_NP_948324-MLA99131522699_112025-F.jpg",
    "tipo": "camada2",
    "enfileirado_em": "2026-07-18T21:13:13.232781+00:00"
  },
  {
    "data": "2026-07-18",
    "product_id": "MLB68384535",
    "nome": "Brinquedo Educativo Celular Infantil Unicórnio Bebê Menina Roxo",
    "preco": 34.5,
    "preco_original": 39.21,
    "n_ofertas": 1,
    "item_id": "MLB4625693211",
    "seller_id": 72890159,
    "frete_gratis": true,
    "full": false,
    "permalink": "https://www.mercadolivre.com.br/p/MLB68384535",
    "imagem": "https://http2.mlstatic.com/D_NQ_NP_814867-MLA110708120935_042026-F.jpg",
    "tipo": "camada2",
    "enfileirado_em": "2026-07-18T21:13:13.232781+00:00"
  }
]