[
  {
    "data": "2026-07-21",
    "product_id": "MLB51508196",
    "nome": "Kit Emily Henry",
    "preco": 63.51,
    "preco_original": 89.9,
    "n_ofertas": 72,
    "item_id": "MLB5501150398",
    "seller_id": 480263032,
    "frete_gratis": true,
    "full": true,
    "permalink": "https://www.mercadolivre.com.br/p/MLB51508196",
    "imagem": "https://http2.mlstatic.com/D_NQ_NP_886955-MLA86541448403_062025-F.jpg",
    "tipo": "camada2",
    "enfileirado_em": "2026-07-21T15:09:36.442075+00:00"
  },
  {
    "data": "2026-07-21",
    "product_id": "MLB29915187",
    "nome": "O mar de monstros: (Série Percy Jackson e os Olimpianos), de Rick Riordan. Série Percy Jackson e os Olimpianos, vol. 2. Editora Intrínseca Ltda., capa mole, edição 1 em português, ",
    "preco": 46.81,
    "preco_original": 69.9,
    "n_ofertas": 72,
    "item_id": "MLB4904119612",
    "seller_id": 480263032,
    "frete_gratis": true,
    "full": true,
    "permalink": "https://www.mercadolivre.com.br/p/MLB29915187",
    "imagem": "https://http2.mlstatic.com/D_NQ_NP_891458-MLU74093013200_012024-F.jpg",
    "tipo": "camada2",
    "enfileirado_em": "2026-07-21T15:09:36.442075+00:00"
  },
  {
    "data": "2026-07-21",
    "product_id": "MLB57813856",
    "nome": "Kit Thrillers Colleen Hoover: Verity + Layla",
    "preco": 66.4,
    "preco_original": 99.9,
    "n_ofertas": 70,
    "item_id": "MLB4353179215",
    "seller_id": 480263032,
    "frete_gratis": true,
    "full": true,
    "permalink": "https://www.mercadolivre.com.br/p/MLB57813856",
    "imagem": "https://http2.mlstatic.com/D_NQ_NP_958851-MLA113421302169_062026-F.jpg",
    "tipo": "camada2",
    "enfileirado_em": "2026-07-21T15:09:36.442075+00:00"
  },
  {
    "data": "2026-07-21",
    "product_id": "MLB19244025",
    "nome": "Alta tensão (Myron Bolitar – Livro 10), de Coben, Harlan. Editora Arqueiro Ltda., capa mole (2019)",
    "preco": 47.53,
    "preco_original": 69.9,
    "n_ofertas": 31,
    "item_id": "MLB4904603894",
    "seller_id": 480263032,
    "frete_gratis": true,
    "full": true,
    "permalink": "https://www.mercadolivre.com.br/p/MLB19244025",
    "imagem": "https://http2.mlstatic.com/D_NQ_NP_753410-MLU50455337414_062022-F.jpg",
    "tipo": "camada2",
    "enfileirado_em": "2026-07-21T15:09:36.442075+00:00"
  },
  {
    "data": "2026-07-21",
    "product_id": "MLB67071973",
    "nome": "Viajando Com Agatha Christie",
    "preco": 65.97,
    "preco_original": null,
    "n_ofertas": 8,
    "item_id": "MLB4801159543",
    "seller_id": 1777224590,
    "frete_gratis": true,
    "full": false,
    "permalink": "https://www.mercadolivre.com.br/p/MLB67071973",
    "imagem": "https://http2.mlstatic.com/D_NQ_NP_722707-MLA108551412654_032026-F.jpg",
    "tipo": "camada2",
    "enfileirado_em": "2026-07-21T15:09:36.442075+00:00"
  },
  {
    "data": "2026-07-21",
    "product_id": "MLB31262713",
    "nome": "Homem Por Tras De O Codigo Da Vinci, O Uma Biografia Nao Autorizada De Dan Brown, De Lisa Rogak. Editora Verus Em Português",
    "preco": 23.14,
    "preco_original": null,
    "n_ofertas": 5,
    "item_id": "MLB4104164195",
    "seller_id": 434855362,
    "frete_gratis": true,
    "full": false,
    "permalink": "https://www.mercadolivre.com.br/p/MLB31262713",
    "imagem": "https://http2.mlstatic.com/D_NQ_NP_892206-MLU77444327627_072024-F.jpg",
    "tipo": "camada2",
    "enfileirado_em": "2026-07-21T15:09:36.442075+00:00"
  },
  {
    "data": "2026-07-21",
    "product_id": "MLB72048964",
    "nome": "A Dona De Casa Perfeita Um Thriller Psicológico Sobre O La",
    "preco": 146.41,
    "preco_original": null,
    "n_ofertas": 2,
    "item_id": "MLB6898752596",
    "seller_id": 44566626,
    "frete_gratis": true,
    "full": false,
    "permalink": "https://www.mercadolivre.com.br/p/MLB72048964",
    "imagem": "https://http2.mlstatic.com/D_NQ_NP_742349-MLA111621941244_062026-F.jpg",
    "tipo": "camada2",
    "enfileirado_em": "2026-07-21T15:09:36.442075+00:00"
  },
  {
    "data": "2026-07-21",
    "product_id": "MLB46202182",
    "nome": "Arcanum Unbounded: The Cosmere Collection, De Brandon Sanderson. Editorial Gollancz, Capa Mole Em Inglês, 2017",
    "preco": 117.0,
    "preco_original": null,
    "n_ofertas": 2,
    "item_id": "MLB5292746670",
    "seller_id": 649963261,
    "frete_gratis": true,
    "full": false,
    "permalink": "https://www.mercadolivre.com.br/p/MLB46202182",
    "imagem": "https://http2.mlstatic.com/D_NQ_NP_886696-MLA82277114138_022025-F.jpg",
    "tipo": "camada2",
    "enfileirado_em": "2026-07-21T15:09:36.442075+00:00"
  },
  {
    "data": "2026-07-21",
    "product_id": "MLB21571425",
    "nome": "Hq Percy Jackson & O Mar De Monstros - Rick Riordan -",
    "preco": 130.0,
    "preco_original": null,
    "n_ofertas": 1,
    "item_id": "MLB6251226560",
    "seller_id": 778271982,
    "frete_gratis": true,
    "full": false,
    "permalink": "https://www.mercadolivre.com.br/p/MLB21571425",
    "imagem": "https://http2.mlstatic.com/D_NQ_NP_819576-MLB29482380266_022019-F.jpg",
    "tipo": "camada2",
    "enfileirado_em": "2026-07-21T15:09:36.442075+00:00"
  },
  {
    "data": "2026-07-21",
    "product_id": "MLB19459679",
    "nome": "Livro O Caminho Dos Reis De Brandon Sanderson Edição 1 2022 Português Editora Trama",
    "preco": 103.0,
    "preco_original": 199.89,
    "n_ofertas": 98,
    "item_id": "MLB4423957539",
    "seller_id": 629557067,
    "frete_gratis": true,
    "full": true,
    "permalink": "https://www.mercadolivre.com.br/p/MLB19459679",
    "imagem": "https://http2.mlstatic.com/D_NQ_NP_738281-MLA112164702040_062026-F.jpg",
    "tipo": "camada2",
    "enfileirado_em": "2026-07-21T15:09:36.442075+00:00"
  },
  {
    "data": "2026-07-21",
    "product_id": "MLB34699232",
    "nome": "Quarta Asa Rebecca Yarros Editorial Planeta Minotauro",
    "preco": 74.63,
    "preco_original": 109.9,
    "n_ofertas": 94,
    "item_id": "MLB5205501016",
    "seller_id": 480263032,
    "frete_gratis": true,
    "full": true,
    "permalink": "https://www.mercadolivre.com.br/p/MLB34699232",
    "imagem": "https://http2.mlstatic.com/D_NQ_NP_745474-MLU75125267112_032024-F.jpg",
    "tipo": "camada2",
    "enfileirado_em": "2026-07-21T15:09:36.442075+00:00"
  },
  {
    "data": "2026-07-21",
    "product_id": "MLB45880915",
    "nome": "Box Magisterium",
    "preco": 178.45,
    "preco_original": null,
    "n_ofertas": 38,
    "item_id": "MLB4043706729",
    "seller_id": 170823796,
    "frete_gratis": true,
    "full": false,
    "permalink": "https://www.mercadolivre.com.br/p/MLB45880915",
    "imagem": "https://http2.mlstatic.com/D_NQ_NP_874812-MLA112270055224_062026-F.jpg",
    "tipo": "camada2",
    "enfileirado_em": "2026-07-21T15:09:36.442075+00:00"
  },
  {
    "data": "2026-07-21",
    "product_id": "MLB30523252",
    "nome": "O segredo da empregada (A empregada – Livro 2), de Freida McFadden. Editora Arqueiro, capa mole, edição 1 em português, 2024",
    "preco": 36.9,
    "preco_original": null,
    "n_ofertas": 75,
    "item_id": "MLB7162379570",
    "seller_id": 3466873516,
    "frete_gratis": true,
    "full": false,
    "permalink": "https://www.mercadolivre.com.br/p/MLB30523252",
    "imagem": "https://http2.mlstatic.com/D_NQ_NP_683379-MLU74262368535_012024-F.jpg",
    "tipo": "camada2",
    "enfileirado_em": "2026-07-21T15:09:36.442075+00:00"
  },
  {
    "data": "2026-07-21",
    "product_id": "MLB34253346",
    "nome": "Kit Loucos Por Livros + Leitura De Verão: Não Aplica, De : Emily Henry / Tradução: Cecília Camargo Bartalotti. Editorial Verus, Tapa Mole En Português, 2022",
    "preco": 117.14,
    "preco_original": 123.31,
    "n_ofertas": 4,
    "item_id": "MLB4518295950",
    "seller_id": 235262653,
    "frete_gratis": true,
    "full": false,
    "permalink": "https://www.mercadolivre.com.br/p/MLB34253346",
    "imagem": "https://http2.mlstatic.com/D_NQ_NP_814498-MLU75015019619_032024-F.jpg",
    "tipo": "camada2",
    "enfileirado_em": "2026-07-21T15:09:36.442075+00:00"
  },
  {
    "data": "2026-07-21",
    "product_id": "MLB72083205",
    "nome": "Kit Thrillers Colleen Hoover: Verity + Layla - Inglês",
    "preco": 193.93,
    "preco_original": null,
    "n_ofertas": 3,
    "item_id": "MLB6895682038",
    "seller_id": 44566626,
    "frete_gratis": true,
    "full": false,
    "permalink": "https://www.mercadolivre.com.br/p/MLB72083205",
    "imagem": "https://http2.mlstatic.com/D_NQ_NP_933268-MLA111624938504_062026-F.jpg",
    "tipo": "camada2",
    "enfileirado_em": "2026-07-21T15:09:36.442075+00:00"
  }
]