[
  {
    "data": "2026-07-20",
    "product_id": "MLB64115842",
    "nome": "Kit A Empregada + O Segredo Da Empregada + A Empregada Está De Olho, De Freida Mcfadden, Vol. 1. Editora Arqueiro, Capa Mole (2024)",
    "preco": 197.99,
    "preco_original": null,
    "n_ofertas": 2,
    "item_id": "MLB4454335621",
    "seller_id": 54564251,
    "frete_gratis": true,
    "full": false,
    "permalink": "https://www.mercadolivre.com.br/p/MLB64115842",
    "imagem": "https://http2.mlstatic.com/D_NQ_NP_705429-MLA104285817215_012026-F.jpg",
    "tipo": "camada2",
    "enfileirado_em": "2026-07-20T18:09:41.453212+00:00"
  }
]